{"lastUsed":1528217891035,"path":"C:\/Users\/Lukas\/project17","projectCount":1,"recentFiles":[{"path":"\/Project17\/src\/project17","parentWorkspace":"C:\/Users\/Lukas\/project17","name":"SimpleMergeMVC.java","lastModified":1528217925242,"locationURI":"file:\/C:\/Users\/Lukas\/project17\/Project17\/src\/project17\/SimpleMergeMVC.java"},{"path":"\/Project17\/src\/project17","parentWorkspace":"C:\/Users\/Lukas\/project17","name":"SimpleMergeView.java","lastModified":1528217848103,"locationURI":"file:\/C:\/Users\/Lukas\/project17\/Project17\/src\/project17\/SimpleMergeView.java"},{"path":"\/Project17\/src\/project17","parentWorkspace":"C:\/Users\/Lukas\/project17","name":"SimpleMergeView2.java","lastModified":1528210020670,"locationURI":"file:\/C:\/Users\/Lukas\/project17\/Project17\/src\/project17\/SimpleMergeView2.java"},{"path":"\/Project17\/src\/project17","parentWorkspace":"C:\/Users\/Lukas\/project17","name":"SimpleMergeController.java","lastModified":1528217894284,"locationURI":"file:\/C:\/Users\/Lukas\/project17\/Project17\/src\/project17\/SimpleMergeController.java"},{"path":"\/Project17\/src\/project17","parentWorkspace":"C:\/Users\/Lukas\/project17","name":"Save.java","lastModified":1528214306187,"locationURI":"file:\/C:\/Users\/Lukas\/project17\/Project17\/src\/project17\/Save.java"},{"path":"\/Project17\/src\/project17","parentWorkspace":"C:\/Users\/Lukas\/project17","name":"Edit.java","lastModified":1528217492854,"locationURI":"file:\/C:\/Users\/Lukas\/project17\/Project17\/src\/project17\/Edit.java"},{"path":"\/Project17","parentWorkspace":"C:\/Users\/Lukas\/project17","name":"Test1","lastModified":1528207549663,"locationURI":"file:\/C:\/Users\/Lukas\/project17\/Project17\/Test1"},{"path":"\/Project17","parentWorkspace":"C:\/Users\/Lukas\/project17","name":"Test2","lastModified":1528207615867,"locationURI":"file:\/C:\/Users\/Lukas\/project17\/Project17\/Test2"},{"path":"\/Project17\/src\/project17","parentWorkspace":"C:\/Users\/Lukas\/project17","name":"Compare.java","lastModified":1528217802888,"locationURI":"file:\/C:\/Users\/Lukas\/project17\/Project17\/src\/project17\/Compare.java"},{"path":"\/Project17\/src\/project17","parentWorkspace":"C:\/Users\/Lukas\/project17","name":"Load.java","lastModified":1528207198602,"locationURI":"file:\/C:\/Users\/Lukas\/project17\/Project17\/src\/project17\/Load.java"}]}